counters/johnson_counter/johnson_counter.v
module johnson_counter(
input clk,rst,
output reg [3:0]q
);
always@(posedge clk)begin
    if(rst)
        q<=4'b0000;
    else
        q<={q[2:0],~q[3]};
end
endmodule

counters/johnson_counter/johnson_counter_tb.v
module tb;
reg clk,rst;
wire [3:0]q;
johnson_counter uut(.clk(clk),.rst(rst),.q(q));
initial clk=0;
always #5 clk=~clk;
initial begin
$dumpfile("wave.vcd");
$dumpvars(0,tb);
$monitor("time=%0t clk=%b rst=%b q=%b",$time,clk,rst,q);
#5;
rst=1;
#10;
rst=0;
#50;
$finish;
end
endmodule

counters/johnson_counter/wave.vcd
$date
	Mon Jul  6 11:50:29 2026
$end
$version
	Icarus Verilog
$end
$timescale
	1s
$end
$scope module tb $end
$var wire 4 ! q [3:0] $end
$var reg 1 " clk $end
$var reg 1 # rst $end
$scope module uut $end
$var wire 1 " clk $end
$var wire 1 # rst $end
$var reg 4 $ q [3:0] $end
$upscope $end
$upscope $end
$enddefinitions $end
$comment Show the parameter values. $end
$dumpall
$end
#0
$dumpvars
bx $
x#
0"
bx !
$end
#5
b0 !
b0 $
1#
1"
#10
0"
#15
b1 !
b1 $
1"
0#
#20
0"
#25
b11 !
b11 $
1"
#30
0"
#35
b111 !
b111 $
1"
#40
0"
#45
b1111 !
b1111 $
1"
#50
0"
#55
b1110 !
b1110 $
1"
#60
0"
#65
b1100 !
b1100 $
1"
