registers/siso_register/siso_register.v
module siso_register(
input clk,rst,
input serial_in,
output reg serial_out
);
reg [3:0]shift_reg;
always@(posedge clk)begin
    if(rst)begin
        serial_out<=1'b0;
    end
    else begin
        serial_out<=shift_reg[0];
        shift_reg<={serial_in,shift_reg[3:1]};
    end
end
endmodule

registers/siso_register/siso_register_tb.v
module tb;
reg clk,rst;
reg serial_in;
wire serial_out;
siso_register uut(.clk(clk),.rst(rst),.serial_in(serial_in),.serial_out(serial_out));
initial clk=0;
always #5 clk=~clk;
initial begin
$dumpfile("wave.vcd");
$dumpvars(0,tb);
$monitor("time=%0t clk=%b rst=%b serial__in=%b shift_reg=%b serial_out=%b",
          $time,clk,rst,serial_in,uut.shift_reg,serial_out);
#5;
rst=1;
serial_in=1'b0;#10;
rst=0;
serial_in=1;#10;
serial_in=1;#10;
serial_in=0;#10;
serial_in=1;#10;
serial_in=0;#40;
$finish;
end
endmodule

registers/siso_register/wave.vcd
$date
	Mon Jul  6 05:48:16 2026
$end
$version
	Icarus Verilog
$end
$timescale
	1s
$end
$scope module tb $end
$var wire 1 ! serial_out $end
$var reg 1 " clk $end
$var reg 1 # rst $end
$var reg 1 $ serial_in $end
$scope module uut $end
$var wire 1 " clk $end
$var wire 1 # rst $end
$var wire 1 $ serial_in $end
$var reg 1 ! serial_out $end
$var reg 4 % shift_reg [3:0] $end
$upscope $end
$upscope $end
$enddefinitions $end
$comment Show the parameter values. $end
$dumpall
$end
#0
$dumpvars
bx %
x$
x#
0"
x!
$end
#5
0!
0$
1#
1"
#10
0"
#15
b1xxx %
x!
1"
1$
0#
#20
0"
#25
b11xx %
1"
#30
0"
#35
b11x %
1"
0$
#40
0"
#45
b1011 %
1"
1$
#50
0"
#55
b101 %
1!
1"
0$
#60
0"
#65
b10 %
1"
#70
0"
#75
b1 %
0!
1"
#80
0"
#85
b0 %
1!
1"
#90
0"
#95
0!
1"
