latches_and_flipflops/master_slave_ff/master_slave_ff.v
module master_slave_ff(
input clk,rst,d,
output reg q,q_bar
);
reg master;
always@(clk or d or rst)begin
    if(rst)
        master<=1'b0;
    else if(clk)
        master <= d;
end
always@(clk or master or rst)begin
    if(rst)begin
        q<=1'b0;
        q_bar<=1'b1;
    end
    else if(!clk)begin
        q<=master;
        q_bar<=~master;
    end
end
endmodule

latches_and_flipflops/master_slave_ff/master_slave_ff_tb.v
module tb;
reg clk,rst,d;
wire q,q_bar;
master_slave_ff uut(.clk(clk),.rst(rst),.d(d),.q(q),.q_bar(q_bar));
initial begin
    clk=0;
   forever #5 clk=~clk;
end
initial begin
$dumpfile("wave.vcd");
$dumpvars(0,tb);
$monitor("time=%0t clk=%b rst=%b d=%b q=%b q_bar=%b",$time,clk,rst,d,q,q_bar);
#5 rst=1;
   d=0;#10;
   rst=0;
   d=1;#10;
   d=0;#10;
   d=1;#10;
$finish;
end
endmodule

latches_and_flipflops/master_slave_ff/wave.vcd
$date
	Thu Jul  2 07:19:50 2026
$end
$version
	Icarus Verilog
$end
$timescale
	1s
$end
$scope module tb $end
$var wire 1 ! q_bar $end
$var wire 1 " q $end
$var reg 1 # clk $end
$var reg 1 $ d $end
$var reg 1 % rst $end
$scope module uut $end
$var wire 1 # clk $end
$var wire 1 $ d $end
$var wire 1 % rst $end
$var reg 1 & master $end
$var reg 1 " q $end
$var reg 1 ! q_bar $end
$upscope $end
$upscope $end
$enddefinitions $end
$comment Show the parameter values. $end
$dumpall
$end
#0
$dumpvars
x&
x%
x$
0#
x"
x!
$end
#5
1!
0"
0&
0$
1%
1#
#10
0#
#15
1&
1#
1$
0%
#20
0!
1"
0#
#25
0&
1#
0$
#30
1!
0"
0#
#35
1&
1#
1$
#40
0!
1"
0#
