latches_and_flipflops/jk_flipflop/jk_flipflop.v
module jk_flipflop(
input clk,j,k,
output reg q,q_bar
);
always@(posedge clk)begin
    case({j,k})
        2'b00:begin
            q<=q;
            q_bar<=~q;
        end
        2'b01:begin
            q<=1'b0;
            q_bar<=1'b1;
        end
        2'b10:begin
            q<=1'b1;
            q_bar<=1'b0;
        end
        2'b11:begin
            q<=~q;
            q_bar<=q;
        end
        default:begin
            q<=1'bx;
            q_bar<=1'bx;
        end
    endcase
end
endmodule

latches_and_flipflops/jk_flipflop/jk_flipflop_tb.v
module tb;
reg clk,j,k;
wire q,q_bar;
jk_flipflop uut(.clk(clk),.j(j),.k(k),.q(q),.q_bar(q_bar));
initial begin
    clk=0;
    forever #5 clk=~clk;
end
initial begin
$dumpfile("wave.vcd");
$dumpvars(0,tb);
$monitor("time=%0t clk=%b j=%b k=%b q=%B q_bar=%b",$time,clk,j,k,q,q_bar);
#5;j=0;k=0;#10;//hold
j=0;k=1;#10;//rst
j=0;k=0;#10;//hold
j=1;k=0;#10;//set
j=0;k=0;#10;//hold
j=1;k=1;#40;//toggle
$finish;
end
endmodule

latches_and_flipflops/jk_flipflop/wave.vcd
$date
	Wed Jul  1 14:09:52 2026
$end
$version
	Icarus Verilog
$end
$timescale
	1s
$end
$scope module tb $end
$var wire 1 ! q_bar $end
$var wire 1 " q $end
$var reg 1 # clk $end
$var reg 1 $ j $end
$var reg 1 % k $end
$scope module uut $end
$var wire 1 # clk $end
$var wire 1 $ j $end
$var wire 1 % k $end
$var reg 1 " q $end
$var reg 1 ! q_bar $end
$upscope $end
$upscope $end
$enddefinitions $end
$comment Show the parameter values. $end
$dumpall
$end
#0
$dumpvars
x%
x$
0#
x"
x!
$end
#5
0%
0$
1#
#10
0#
#15
1!
0"
1#
1%
#20
0#
#25
1#
0%
#30
0#
#35
0!
1"
1#
1$
#40
0#
#45
1#
0$
#50
0#
#55
1!
0"
1#
1%
1$
#60
0#
#65
0!
1"
1#
#70
0#
#75
1!
0"
1#
#80
0#
#85
0!
1"
1#
#90
0#
#95
1!
0"
1#
