registers/register_8bit/register_8bit.v
module register_8bit(
input clk,rst,
input [7:0]d,
output reg [7:0]q
);
always@(posedge clk)begin
    if (rst)
        q<=8'b00000000;
    else
        q<=d;
end
endmodule

registers/register_8bit/register_8bit_tb.v
module tb;
reg clk,rst;
reg[7:0]d;
wire[7:0]q;
integer i;
register_8bit uut(.clk(clk),.rst(rst),.d(d),.q(q));
initial clk=0;
always #5 clk=~clk;
initial begin 
$dumpfile("wave.vcd");
$dumpvars(0,tb);
$monitor("time=%0t clk=%b rst=%b d=%b q=%b",$time,clk,rst,d,q);
#5;
rst=1;
d=8'b00000000;#10;
rst=0;
for(i=0;i<16;i=i+1)begin
    d=i;#10;
end
$finish;
end
endmodule

registers/register_8bit/wave.vcd
$date
	Sat Jul  4 03:57:43 2026
$end
$version
	Icarus Verilog
$end
$timescale
	1s
$end
$scope module tb $end
$var wire 8 ! q [7:0] $end
$var reg 1 " clk $end
$var reg 8 # d [7:0] $end
$var reg 1 $ rst $end
$var integer 32 % i [31:0] $end
$scope module uut $end
$var wire 1 " clk $end
$var wire 8 & d [7:0] $end
$var wire 1 $ rst $end
$var reg 8 ' q [7:0] $end
$upscope $end
$upscope $end
$enddefinitions $end
$comment Show the parameter values. $end
$dumpall
$end
#0
$dumpvars
bx '
bx &
bx %
x$
bx #
0"
bx !
$end
#5
b0 !
b0 '
b0 #
b0 &
1$
1"
#10
0"
#15
1"
b0 %
0$
#20
0"
#25
b1 !
b1 '
1"
b1 #
b1 &
b1 %
#30
0"
#35
b10 !
b10 '
1"
b10 #
b10 &
b10 %
#40
0"
#45
b11 !
b11 '
1"
b11 #
b11 &
b11 %
#50
0"
#55
b100 !
b100 '
1"
b100 #
b100 &
b100 %
#60
0"
#65
b101 !
b101 '
1"
b101 #
b101 &
b101 %
#70
0"
#75
b110 !
b110 '
1"
b110 #
b110 &
b110 %
#80
0"
#85
b111 !
b111 '
1"
b111 #
b111 &
b111 %
#90
0"
#95
b1000 !
b1000 '
1"
b1000 #
b1000 &
b1000 %
#100
0"
#105
b1001 !
b1001 '
1"
b1001 #
b1001 &
b1001 %
#110
0"
#115
b1010 !
b1010 '
1"
b1010 #
b1010 &
b1010 %
#120
0"
#125
b1011 !
b1011 '
1"
b1011 #
b1011 &
b1011 %
#130
0"
#135
b1100 !
b1100 '
1"
b1100 #
b1100 &
b1100 %
#140
0"
#145
b1101 !
b1101 '
1"
b1101 #
b1101 &
b1101 %
#150
0"
#155
b1110 !
b1110 '
1"
b1110 #
b1110 &
b1110 %
#160
0"
#165
b1111 !
b1111 '
1"
b1111 #
b1111 &
b1111 %
#170
0"
#175
1"
b10000 %
