finite_state_machines/sequence_detector_1101/sequence_detector_1101.v
module  sequence_detector_1101(
    input clk,rst,in,
    output reg out,
    output [2:0]state_dbg
);
reg[2:0]state,next_state;

assign state_dbg=state;

parameter
      s0=3'b000,
      s1=3'b001,
      s2=3'b010,
      s3=3'b011,
      s4=3'b100;

always@(posedge clk)begin
    if(rst)
        state<=s0;
    else
        state<=next_state;
end

always@(*)begin
    case(state)
        s0:
            if(in)
                next_state=s1;
            else
                next_state=s0;
        s1:
            if(in)
                next_state=s2;
            else
                next_state=s0;
        s2:
            if(in)
                next_state=s2;
            else
                next_state=s3;
        s3:
            if(in)
                next_state=s4;
            else
                next_state=s0;
        s4:
            if(in)
                next_state=s2;
            else
                next_state=s0;

            default: next_state=s0;
        endcase
    end

always@(*)begin
   if(state==s4)
      out=1'b1;
   else  
      out=1'b0; 
 end
endmodule

finite_state_machines/sequence_detector_1101/sequence_detector_1101_tb.v
module tb;
reg clk,rst,in;
wire out;
wire [2:0]state_dbg;
sequence_detector_1101 uut(.clk(clk),.rst(rst),.in(in),.state_dbg(state_dbg),.out(out));
initial clk=0;
always #5 clk=~clk;
initial begin
$dumpfile("wave.vcd");
$dumpvars(0,tb);
$monitor("time=%0t clk=%b rst=%b in=%b state_dbg=%b out=%b",$time,clk,rst,in,state_dbg,out);
#5;
rst=1;
in=0;
#10;
rst=0;

$display("test--1");
@(negedge clk);
in=0;
@(negedge clk);
in=1;
@(negedge clk);
in=1;
@(negedge clk);
in=0;
@(negedge clk);
in=1;
@(negedge clk);
in=1;
@(negedge clk);
in=0;
@(negedge clk);
in=1;
#10;

$display("test--2");
@(negedge clk);
in=0;
@(negedge clk);
in=1;
@(negedge clk);
in=1;
@(negedge clk);
in=0;
@(negedge clk);
in=0;
@(negedge clk);
in=1;
@(negedge clk);
in=1;
@(negedge clk);
in=0;
@(negedge clk);
in=1;
#20;
$finish;
end
endmodule

finite_state_machines/sequence_detector_1101/wave.vcd
$date
	Tue Jul  7 09:40:55 2026
$end
$version
	Icarus Verilog
$end
$timescale
	1s
$end
$scope module tb $end
$var wire 3 ! state_dbg [2:0] $end
$var wire 1 " out $end
$var reg 1 # clk $end
$var reg 1 $ in $end
$var reg 1 % rst $end
$scope module uut $end
$var wire 1 # clk $end
$var wire 1 $ in $end
$var wire 1 % rst $end
$var wire 3 & state_dbg [2:0] $end
$var parameter 3 ' s0 $end
$var parameter 3 ( s1 $end
$var parameter 3 ) s2 $end
$var parameter 3 * s3 $end
$var parameter 3 + s4 $end
$var reg 3 , next_state [2:0] $end
$var reg 1 " out $end
$var reg 3 - state [2:0] $end
$upscope $end
$upscope $end
$enddefinitions $end
$comment Show the parameter values. $end
$dumpall
b100 +
b11 *
b10 )
b1 (
b0 '
$end
#0
$dumpvars
bx -
bx ,
bx &
x%
x$
0#
x"
bx !
$end
#5
0"
b0 !
b0 &
b0 -
b0 ,
0$
1%
1#
#10
0#
#15
1#
0%
#20
0#
#25
1#
#30
b1 ,
1$
0#
#35
b10 ,
b1 !
b1 &
b1 -
1#
#40
0#
#45
b10 !
b10 &
b10 -
1#
#50
b11 ,
0$
0#
#55
b0 ,
b11 !
b11 &
b11 -
1#
#60
b100 ,
1$
0#
#65
1"
b10 ,
b100 !
b100 &
b100 -
1#
#70
0#
#75
0"
b10 !
b10 &
b10 -
1#
#80
b11 ,
0$
0#
#85
b0 ,
b11 !
b11 &
b11 -
1#
#90
b100 ,
1$
0#
#95
1"
b10 ,
b100 !
b100 &
b100 -
1#
#100
b0 ,
0$
0#
#105
0"
b0 !
b0 &
b0 -
1#
#110
b1 ,
1$
0#
#115
b10 ,
b1 !
b1 &
b1 -
1#
#120
0#
#125
b10 !
b10 &
b10 -
1#
#130
b11 ,
0$
0#
#135
b0 ,
b11 !
b11 &
b11 -
1#
#140
0#
#145
b0 !
b0 &
b0 -
1#
#150
b1 ,
1$
0#
#155
b10 ,
b1 !
b1 &
b1 -
1#
#160
0#
#165
b10 !
b10 &
b10 -
1#
#170
b11 ,
0$
0#
#175
b0 ,
b11 !
b11 &
b11 -
1#
#180
b100 ,
1$
0#
#185
1"
b10 ,
b100 !
b100 &
b100 -
1#
#190
0#
#195
0"
b10 !
b10 &
b10 -
1#
