counters/up_counter/up_counter.v
module up_counter(
input clk,rst,
output reg [3:0]count
);
always@(posedge clk)begin
    if(rst)
        count<=4'b0000;
    else
        count<=count+1'b1;
end
endmodule

counters/up_counter/up_counter_tb.v
module tb;
reg clk,rst;
wire [3:0]count;
up_counter uut(.clk(clk),.rst(rst),.count(count));
initial clk=0;
always #5 clk=~clk;
initial begin
$dumpfile("wave.vcd");
$dumpvars(0,tb);
$monitor("time=%0t clk=%b rst=%b count=%b",$time,clk,rst,count);
#5;
rst=1;
#10;
rst=0;
#170;
$finish;
end
endmodule

counters/up_counter/wave.vcd
$date
	Mon Jul  6 09:43:02 2026
$end
$version
	Icarus Verilog
$end
$timescale
	1s
$end
$scope module tb $end
$var wire 4 ! count [3:0] $end
$var reg 1 " clk $end
$var reg 1 # rst $end
$scope module uut $end
$var wire 1 " clk $end
$var wire 1 # rst $end
$var reg 4 $ count [3:0] $end
$upscope $end
$upscope $end
$enddefinitions $end
$comment Show the parameter values. $end
$dumpall
$end
#0
$dumpvars
bx $
x#
0"
bx !
$end
#5
b0 !
b0 $
1#
1"
#10
0"
#15
b1 !
b1 $
1"
0#
#20
0"
#25
b10 !
b10 $
1"
#30
0"
#35
b11 !
b11 $
1"
#40
0"
#45
b100 !
b100 $
1"
#50
0"
#55
b101 !
b101 $
1"
#60
0"
#65
b110 !
b110 $
1"
#70
0"
#75
b111 !
b111 $
1"
#80
0"
#85
b1000 !
b1000 $
1"
#90
0"
#95
b1001 !
b1001 $
1"
#100
0"
#105
b1010 !
b1010 $
1"
#110
0"
#115
b1011 !
b1011 $
1"
#120
0"
#125
b1100 !
b1100 $
1"
#130
0"
#135
b1101 !
b1101 $
1"
#140
0"
#145
b1110 !
b1110 $
1"
#150
0"
#155
b1111 !
b1111 $
1"
#160
0"
#165
b0 !
b0 $
1"
#170
0"
#175
b1 !
b1 $
1"
#180
0"
#185
b10 !
b10 $
1"
