finite_state_machines/mealy_fsm/mealy_fsm.v
module mealy_fsm(
    input clk,rst,in,
    output reg out,
    output [1:0]state_dbg
);
reg [1:0]state,next_state;
assign state_dbg=state;

parameter
    s0=2'b00,
    s1=2'b01,
    s2=2'b10;

always@(posedge clk)begin
    if(rst)
        state<=s0;
    else
        state<=next_state;
end

always@(*)begin
    case(state)
        s0:
            if(in)
                next_state=s1;
            else
                next_state=s0;
        s1:
            if(in)
                next_state=s1;
            else
                next_state=s2;
        s2:
            if(in)
                next_state=s0;
            else
                next_state=s2;

            default:next_state=s0;
        endcase
    end
    always@(*)begin
        case(state)
         s2:
            if(in)
                out=1'b1;
            else
                out=1'b0;

            default:out=1'b0;
        endcase
    end
    endmodule

finite_state_machines/mealy_fsm/mealy_fsm_tb.v
module tb;
reg clk,rst,in;
wire out;
wire[1:0]state_dbg;
mealy_fsm uut(.clk(clk),.rst(rst),.in(in),.state_dbg(state_dbg),.out(out));
initial clk=0;
always #5 clk=~clk;
initial begin
$dumpfile("wave.vcd");
$dumpvars(0,tb);
$monitor("time=%0t clk=%b rst=%b in=%b state_dbg=%b out=%b",$time,clk,rst,in,state_dbg,out);
#5;
rst=1;
in=0;
#10;
rst=0;
@(negedge clk);
in=0;
@(negedge clk);
in=1;
@(negedge clk);
in=0;
@(negedge clk);
in=0;
@(negedge clk);
in=1;
@(negedge clk);
in=1;
@(negedge clk);
in=0;
@(negedge clk);
in=1;
@(negedge clk);
in=0;
#20;
$finish;
end
endmodule

finite_state_machines/mealy_fsm/wave.vcd
$date
	Tue Jul  7 07:03:36 2026
$end
$version
	Icarus Verilog
$end
$timescale
	1s
$end
$scope module tb $end
$var wire 2 ! state_dbg [1:0] $end
$var wire 1 " out $end
$var reg 1 # clk $end
$var reg 1 $ in $end
$var reg 1 % rst $end
$scope module uut $end
$var wire 1 # clk $end
$var wire 1 $ in $end
$var wire 1 % rst $end
$var wire 2 & state_dbg [1:0] $end
$var parameter 2 ' s0 $end
$var parameter 2 ( s1 $end
$var parameter 2 ) s2 $end
$var reg 2 * next_state [1:0] $end
$var reg 1 " out $end
$var reg 2 + state [1:0] $end
$upscope $end
$upscope $end
$enddefinitions $end
$comment Show the parameter values. $end
$dumpall
b10 )
b1 (
b0 '
$end
#0
$dumpvars
bx +
bx *
bx &
x%
x$
0#
x"
bx !
$end
#5
b0 !
b0 &
b0 +
0"
b0 *
0$
1%
1#
#10
0#
#15
1#
0%
#20
0#
#25
1#
#30
b1 *
1$
0#
#35
b1 !
b1 &
b1 +
1#
#40
b10 *
0$
0#
#45
b10 !
b10 &
b10 +
1#
#50
0#
#55
1#
#60
1"
b0 *
1$
0#
#65
b1 *
0"
b0 !
b0 &
b0 +
1#
#70
0#
#75
b1 !
b1 &
b1 +
1#
#80
b10 *
0$
0#
#85
b10 !
b10 &
b10 +
1#
#90
b0 *
1"
1$
0#
#95
0"
b1 *
b0 !
b0 &
b0 +
1#
#100
b0 *
0$
0#
