registers/bidirectional_shift_register/bidirectional_shift_register.v
module bidirectional_shift_register(
input clk,rst,serial_left,serial_right,select,
output reg [3:0]q
);
always@(posedge clk)begin
    if(rst)begin
       q<=4'b0000;
   end
    else begin
        if(select==0)
            q<={q[2:0],serial_left};
        else
            q<={serial_right,q[3:1]};
    end
end
endmodule

registers/bidirectional_shift_register/bidirectional_shift_register_tb.v
module tb;
reg clk,rst,serial_left,serial_right,select;
wire[3:0]q;
bidirectional_shift_register uut(.clk(clk),.rst(rst),.serial_left(serial_left),
    .serial_right(serial_right),.select(select),.q(q));
initial clk=0;
always #5 clk=~clk;
initial begin
$dumpfile("wave.vcd");
$dumpvars(0,tb);
$monitor("time=%0t clk=%b rst=%b serial_left=%b serial_right=%b select=%b q=%b",$time,clk,rst,
         serial_left,serial_right,select,q);
#5;
rst=1;
select=0;
serial_left=0;
serial_right=0;
#10;
rst=0;
select=0;
serial_left=1;
serial_right=0;#10;
serial_left=0;
#20;
select=1;
serial_left=0;
serial_right=1;#10;
serial_right=0;
#20;
$finish;
end
endmodule

registers/bidirectional_shift_register/wave.vcd
$date
	Mon Jul  6 07:45:07 2026
$end
$version
	Icarus Verilog
$end
$timescale
	1s
$end
$scope module tb $end
$var wire 4 ! q [3:0] $end
$var reg 1 " clk $end
$var reg 1 # rst $end
$var reg 1 $ select $end
$var reg 1 % serial_left $end
$var reg 1 & serial_right $end
$scope module uut $end
$var wire 1 " clk $end
$var wire 1 # rst $end
$var wire 1 $ select $end
$var wire 1 % serial_left $end
$var wire 1 & serial_right $end
$var reg 4 ' q [3:0] $end
$upscope $end
$upscope $end
$enddefinitions $end
$comment Show the parameter values. $end
$dumpall
$end
#0
$dumpvars
bx '
x&
x%
x$
x#
0"
bx !
$end
#5
b0 !
b0 '
0&
0%
0$
1#
1"
#10
0"
#15
b1 !
b1 '
1"
1%
0#
#20
0"
#25
b10 !
b10 '
1"
0%
#30
0"
#35
b100 !
b100 '
1"
#40
0"
#45
b1010 !
b1010 '
1"
1&
1$
#50
0"
#55
b101 !
b101 '
1"
0&
#60
0"
#65
b10 !
b10 '
1"
#70
0"
#75
b1 !
b1 '
1"
