registers/piso_register/piso_register.v
module piso_register(
input clk,rst,load,
input [3:0]d,
output reg serial_out
);
reg [3:0]shift_reg;
always@(posedge clk) begin
    if (rst) begin
        shift_reg<=4'b0000;
        serial_out<=1'b0;
    end
    else if(load)begin
        shift_reg<=d;
    end
    else begin
        serial_out<=shift_reg[3];
        shift_reg<={shift_reg[2:0],1'b0};
    end
end
endmodule

registers/piso_register/piso_register_tb.v
module tb;
reg clk,rst,load;
reg [3:0]d;
wire serial_out;
piso_register uut(.clk(clk),.rst(rst),.load(load),.d(d),.serial_out(serial_out));
initial clk=0;
always #5 clk=~clk;
initial begin
$dumpfile("wave.vcd");
$dumpvars(0,tb);
$monitor("time=%0t clk=%b rst=%b load=%b d=%b serial_out=%b",$time,clk,rst,load,d,serial_out);
    rst=1;//rst
    load=0;
    d=4'b0000;#10;

    rst=0;//load
    load=1;
    d=4'b1010;#10;

    load=0;//shift operation.
    #50;
$finish;
end
endmodule

registers/piso_register/wave.vcd
$date
	Sat Jul  4 05:58:26 2026
$end
$version
	Icarus Verilog
$end
$timescale
	1s
$end
$scope module tb $end
$var wire 1 ! serial_out $end
$var reg 1 " clk $end
$var reg 4 # d [3:0] $end
$var reg 1 $ load $end
$var reg 1 % rst $end
$scope module uut $end
$var wire 1 " clk $end
$var wire 4 & d [3:0] $end
$var wire 1 $ load $end
$var wire 1 % rst $end
$var reg 1 ! serial_out $end
$var reg 4 ' shift_reg [3:0] $end
$upscope $end
$upscope $end
$enddefinitions $end
$comment Show the parameter values. $end
$dumpall
$end
#0
$dumpvars
bx '
b0 &
1%
0$
b0 #
0"
x!
$end
#5
0!
b0 '
1"
#10
0"
b1010 #
b1010 &
1$
0%
#15
b1010 '
1"
#20
0"
0$
#25
b100 '
1!
1"
#30
0"
#35
b1000 '
0!
1"
#40
0"
#45
b0 '
1!
1"
#50
0"
#55
0!
1"
