registers/sipo_register/sipo_register.v
module sipo_register(
input clk,rst,serial_in,
output reg [3:0]parallel_out
);
always@(posedge clk)begin
    if(rst)
        parallel_out<=4'b0000;
    else
        parallel_out<={parallel_out[2:0],serial_in};
end
endmodule

registers/sipo_register/sipo_register_tb.v
module tb;
reg clk,rst,serial_in;
wire [3:0]parallel_out;
sipo_register uut(.clk(clk),.rst(rst),.serial_in(serial_in),.parallel_out(parallel_out));
initial clk=0;
always #5 clk=~clk;
initial begin
$dumpfile("wave.vcd");
$dumpvars(0,tb);
$monitor("time=%0t clk=%b rst=%b serial_in=%b parallel_out=%b",$time,clk,rst,serial_in,parallel_out);
rst=1;
serial_in=1'b0;
#10;
rst=0;
serial_in=1'b1;#10;
serial_in=1'b0;#10;
serial_in=1'b1;#10;
serial_in=1'b1;#10;
$finish;
end
endmodule

registers/sipo_register/wave.vcd
$date
	Sat Jul  4 06:42:32 2026
$end
$version
	Icarus Verilog
$end
$timescale
	1s
$end
$scope module tb $end
$var wire 4 ! parallel_out [3:0] $end
$var reg 1 " clk $end
$var reg 1 # rst $end
$var reg 1 $ serial_in $end
$scope module uut $end
$var wire 1 " clk $end
$var wire 1 # rst $end
$var wire 1 $ serial_in $end
$var reg 4 % parallel_out [3:0] $end
$upscope $end
$upscope $end
$enddefinitions $end
$comment Show the parameter values. $end
$dumpall
$end
#0
$dumpvars
bx %
0$
1#
0"
bx !
$end
#5
b0 !
b0 %
1"
#10
0"
1$
0#
#15
b1 !
b1 %
1"
#20
0"
0$
#25
b10 !
b10 %
1"
#30
0"
1$
#35
b101 !
b101 %
1"
#40
0"
#45
b1011 !
b1011 %
1"
