counters/ring_counter/ring_counter.v
module ring_counter(
input clk,rst,
output reg [3:0]q
);
always @(posedge clk) begin
    if (rst)
        q <= 4'b0001;
    else
        q <= {q[2:0], q[3]};
end
endmodule

counters/ring_counter/ring_counter_tb.v
module tb;
reg clk,rst;
wire[3:0]q;
ring_counter uut(.clk(clk),.rst(rst),.q(q));
initial clk=0;
always #5 clk=~clk;
initial begin
$dumpfile("wave.vcd");
$dumpvars(0,tb);
$monitor("time=%0t clk=%b rst=%b count=%b",$time,clk,rst,q);
#5;
rst=1;
#10;
rst=0;
#50;
$finish;
end
endmodule

counters/ring_counter/wave.vcd
$date
	Mon Jul  6 11:32:54 2026
$end
$version
	Icarus Verilog
$end
$timescale
	1s
$end
$scope module tb $end
$var wire 4 ! q [3:0] $end
$var reg 1 " clk $end
$var reg 1 # rst $end
$scope module uut $end
$var wire 1 " clk $end
$var wire 1 # rst $end
$var reg 4 $ q [3:0] $end
$upscope $end
$upscope $end
$enddefinitions $end
$comment Show the parameter values. $end
$dumpall
$end
#0
$dumpvars
bx $
x#
0"
bx !
$end
#5
b1 !
b1 $
1#
1"
#10
0"
#15
b10 !
b10 $
1"
0#
#20
0"
#25
b100 !
b100 $
1"
#30
0"
#35
b1000 !
b1000 $
1"
#40
0"
#45
b1 !
b1 $
1"
#50
0"
#55
b10 !
b10 $
1"
#60
0"
#65
b100 !
b100 $
1"
