latches_and_flipflops/t_flipflop/t_flipflop.v
module t_flipflop(
input clk,rst,t,
output reg q,q_bar
);
always@(posedge clk)begin
    if (rst)begin
        q<=1'b0;
        q_bar<=1'b1;
    end
    else begin
        case(t)
            1'b0:begin
                q<=q;
                q_bar<=~q;
            end
            1'b1:begin
                q<=~q;
                q_bar<=q;
            end
            default:begin
                q<=1'bx;
                q_bar<=1'bx;
            end
        endcase
    end
end
endmodule

latches_and_flipflops/t_flipflop/t_flipflop_tb.v
module tb;
reg clk,rst,t;
wire q,q_bar;
t_flipflop uut(.clk(clk),.rst(rst),.t(t),.q(q),.q_bar(q_bar));
initial begin
    clk=0;
    forever #5 clk=~clk;
end
initial begin
$dumpfile("wave.vcd");
$dumpvars(0,tb);
$monitor("time=%0t clk=%b rst=%b t=%b q=%b q_bar=%b",$time,clk,rst,t,q,q_bar);

 rst=1;
 t=0;#10;
 rst=0;#5;
 t=0;#10;
 t=1;#10;
 t=0;#10;
 t=1;#30;
$finish;
end
endmodule

latches_and_flipflops/t_flipflop/wave.vcd
$date
	Wed Jul  1 15:20:38 2026
$end
$version
	Icarus Verilog
$end
$timescale
	1s
$end
$scope module tb $end
$var wire 1 ! q_bar $end
$var wire 1 " q $end
$var reg 1 # clk $end
$var reg 1 $ rst $end
$var reg 1 % t $end
$scope module uut $end
$var wire 1 # clk $end
$var wire 1 $ rst $end
$var wire 1 % t $end
$var reg 1 " q $end
$var reg 1 ! q_bar $end
$upscope $end
$upscope $end
$enddefinitions $end
$comment Show the parameter values. $end
$dumpall
$end
#0
$dumpvars
0%
1$
0#
x"
x!
$end
#5
1!
0"
1#
#10
0#
0$
#15
1#
#20
0#
#25
0!
1"
1#
1%
#30
0#
#35
1#
0%
#40
0#
#45
1!
0"
1#
1%
#50
0#
#55
0!
1"
1#
#60
0#
#65
1!
0"
1#
#70
0#
#75
0!
1"
1#
