counters/asynchronous_counter/asynchronous_counter.v
module asynchronous_counter(
    input clk,
    input rst,
    output reg [2:0] count
);

always @(posedge clk or posedge rst) begin
    if (rst)
        count <= 3'b000;
    else
        count <= count + 1'b1;
end

endmodule

counters/asynchronous_counter/asynchronous_counter_tb.v
module tb;
reg clk,rst;
wire [2:0]count;
asynchronous_counter uut(.clk(clk),.rst(rst),.count(count));
initial clk=0;
always #5 clk=~clk;
initial begin
$dumpfile("wave.vcd");
$dumpvars(0,tb);
$monitor("time=%0t clk=%b rst=%b count=%b",$time,clk,rst,count);
#5;
rst=1;
#10;
rst=0;
#100;
$finish;
end
endmodule

counters/asynchronous_counter/wave.vcd
$date
	Tue Jul  7 03:36:47 2026
$end
$version
	Icarus Verilog
$end
$timescale
	1s
$end
$scope module tb $end
$var wire 3 ! count [2:0] $end
$var reg 1 " clk $end
$var reg 1 # rst $end
$scope module uut $end
$var wire 1 " clk $end
$var wire 1 # rst $end
$var reg 3 $ count [2:0] $end
$upscope $end
$upscope $end
$enddefinitions $end
$comment Show the parameter values. $end
$dumpall
$end
#0
$dumpvars
bx $
x#
0"
bx !
$end
#5
b0 !
b0 $
1#
1"
#10
0"
#15
b1 !
b1 $
1"
0#
#20
0"
#25
b10 !
b10 $
1"
#30
0"
#35
b11 !
b11 $
1"
#40
0"
#45
b100 !
b100 $
1"
#50
0"
#55
b101 !
b101 $
1"
#60
0"
#65
b110 !
b110 $
1"
#70
0"
#75
b111 !
b111 $
1"
#80
0"
#85
b0 !
b0 $
1"
#90
0"
#95
b1 !
b1 $
1"
#100
0"
#105
b10 !
b10 $
1"
#110
0"
#115
b11 !
b11 $
1"
